{"0":{"color":5,"errors":94,"pairs":[[5,4],[4,5],[2,4],[4,0],[3,5],[3,4],[3,2],[4,3],[2,2],[5,1]],"size":3,"solutions":35,"spl":15,"time":0.0},"1":{"color":3,"errors":6647,"pairs":[[1,0],[2,3],[2,4],[1,2],[3,1],[1,1]],"size":3,"solutions":651,"spl":11,"time":0.0},"10":{"color":4,"errors":140,"pairs":[[5,3],[3,2],[3,4],[3,3],[4,4],[5,2],[0,0],[3,0]],"size":3,"solutions":34,"spl":15,"time":0.0},"100":{"color":5,"errors":149,"pairs":[[4,1],[5,2],[2,0],[1,2],[2,4],[3,4],[4,5],[4,4],[4,2],[2,2]],"size":3,"solutions":122,"spl":10,"time":0.0007849999819882214},"101":{"color":5,"errors":126,"pairs":[[1,1],[3,0],[3,5],[4,2],[4,0],[3,1],[1,0],[2,4],[4,4],[5,3]],"size":3,"solutions":18,"spl":14,"time":0.0002280000044265762},"102":{"color":3,"errors":936,"pairs":[[5,4],[4,2],[0,0],[4,3],[4,5],[1,2]],"size":3,"solutions":321,"spl":12,"time":0.0017729999963194132},"103":{"color":3,"errors":432,"pairs":[[5,4],[3,5],[4,3],[1,0],[5,1],[5,3]],"size":3,"solutions":35,"spl":10,"time":0.00046499999007210135},"104":{"color":3,"errors":846,"pairs":[[2,0],[0,0],[3,2],[2,2],[3,0],[5,1]],"size":3,"solutions":2161,"spl":6,"time":0.0034719998948276043},"105":{"color":3,"errors":351,"pairs":[[4,2],[1,2],[4,3],[3,4],[4,0],[4,1]],"size":3,"solutions":445,"spl":8,"time":0.0015950000379234552},"106":{"color":3,"errors":520,"pairs":[[1,2],[4,3],[5,1],[4,1],[3,5],[3,4]],"size":3,"solutions":782,"spl":7,"time":0.002131999935954809},"107":{"color":4,"errors":1672,"pairs":[[0,0],[1,2],[4,4],[4,5],[2,3],[3,2],[5,1],[2,0]],"size":3,"solutions":1638,"spl":8,"time":0.003986000083386898},"108":{"color":4,"errors":584,"pairs":[[2,0],[4,0],[2,1],[0,0],[2,4],[4,3],[4,4],[3,4]],"size":3,"solutions":226,"spl":10,"time":0.0015650000423192978},"109":{"color":3,"errors":1655,"pairs":[[5,2],[2,2],[2,3],[2,1],[1,0],[2,0]],"size":3,"solutions":378,"spl":6,"time":0.0022360000293701887},"11":{"color":4,"errors":722,"pairs":[[0,0],[4,5],[3,2],[4,2],[2,0],[1,1],[5,2],[5,1]],"size":3,"solutions":121,"spl":8,"time":0.0},"110":{"color":3,"errors":2223,"pairs":[[2,0],[4,0],[1,1],[2,4],[4,3],[3,5]],"size":3,"solutions":303,"spl":7,"time":0.0025549998972564936},"111":{"color":3,"errors":246,"pairs":[[3,5],[5,0],[4,4],[2,3],[3,3],[4,1]],"size":3,"solutions":130,"spl":13,"time":0.0008789999992586672},"112":{"color":3,"errors":158,"pairs":[[2,0],[5,1],[3,2],[4,2],[4,3],[3,1]],"size":3,"solutions":374,"spl":9,"time":0.0016189999878406525},"113":{"color":3,"errors":3699,"pairs":[[2,0],[2,4],[1,2],[2,2],[3,5],[5,2]],"size":3,"solutions":50,"spl":15,"time":0.0018850000342354178},"114":{"color":3,"errors":880,"pairs":[[1,2],[4,3],[3,2],[5,5],[5,1],[2,1]],"size":3,"solutions":125,"spl":13,"time":0.00120900000911206},"115":{"color":3,"errors":1011,"pairs":[[2,3],[5,3],[3,5],[1,0],[3,2],[4,0]],"size":3,"solutions":24,"spl":11,"time":0.0007660000119358301},"116":{"color":3,"errors":373,"pairs":[[3,1],[3,0],[4,0],[2,0],[4,3],[3,3]],"size":3,"solutions":240,"spl":8,"time":0.0013229999458417296},"117":{"color":3,"errors":781,"pairs":[[5,3],[4,1],[2,1],[2,2],[4,3],[2,4]],"size":3,"solutions":76,"spl":8,"time":0.000901999999769032},"118":{"color":4,"errors":630,"pairs":[[5,2],[5,4],[0,0],[2,3],[4,3],[4,0],[1,0],[4,5]],"size":3,"solutions":6,"spl":15,"time":0.0004450000124052167},"119":{"color":4,"errors":424,"pairs":[[4,4],[5,3],[4,2],[1,0],[3,4],[3,2],[3,1],[0,0]],"size":3,"solutions":90,"spl":13,"time":0.000737000023946166},"12":{"color":4,"errors":308,"pairs":[[2,2],[3,4],[4,4],[5,4],[5,3],[4,2],[3,0],[2,0]],"size":3,"solutions":711,"spl":6,"time":0.0},"120":{"color":4,"errors":129,"pairs":[[4,2],[5,2],[3,5],[2,3],[5,4],[2,0],[4,4],[4,5]],"size":3,"solutions":48,"spl":10,"time":0.0003659999929368496},"121":{"color":5,"errors":78,"pairs":[[4,2],[4,0],[4,5],[3,2],[3,4],[3,5],[2,2],[1,2],[5,3],[5,4]],"size":3,"solutions":18,"spl":11,"time":0.0001990000018849969},"122":{"color":5,"errors":400,"pairs":[[2,3],[2,4],[2,2],[3,3],[5,0],[1,2],[3,5],[4,3],[2,1],[5,2]],"size":3,"solutions":98,"spl":15,"time":0.0008340000058524311},"123":{"color":3,"errors":1615,"pairs":[[4,4],[1,0],[5,5],[5,4],[4,0],[5,3]],"size":3,"solutions":818,"spl":9,"time":0.002607000060379505},"124":{"color":3,"errors":2246,"pairs":[[1,2],[5,5],[4,2],[0,0],[4,0],[3,0]],"size":3,"solutions":742,"spl":11,"time":0.002644999884068966},"125":{"color":3,"errors":2469,"pairs":[[1,0],[3,0],[5,2],[2,4],[0,0],[1,1]],"size":3,"solutions":1390,"spl":9,"time":0.003114999970421195},"126":{"color":3,"errors":1273,"pairs":[[2,1],[3,4],[2,3],[3,3],[5,1],[1,0]],"size":3,"solutions":244,"spl":12,"time":0.0018080000299960375},"127":{"color":3,"errors":1751,"pairs":[[4,0],[2,0],[0,0],[4,1],[5,4],[1,2]],"size":3,"solutions":255,"spl":12,"time":0.0019600000232458115},"128":{"color":3,"errors":1348,"pairs":[[5,0],[2,4],[4,2],[2,1],[3,2],[5,5]],"size":3,"solutions":444,"spl":15,"time":0.0021989999804645777},"129":{"color":3,"errors":6120,"pairs":[[3,4],[1,0],[5,5],[5,2],[2,1],[0,0]],"size":3,"solutions":627,"spl":12,"time":0.003266999963670969},"13":{"color":4,"errors":371,"pairs":[[3,5],[3,0],[4,2],[3,3],[0,0],[2,4],[5,2],[4,5]],"size":3,"solutions":60,"spl":14,"time":0.0},"130":{"color":3,"errors":1804,"pairs":[[3,0],[2,0],[1,0],[1,2],[4,1],[4,3]],"size":3,"solutions":2407,"spl":5,"time":0.0028570001013576984},"131":{"color":4,"errors":159,"pairs":[[3,4],[4,4],[4,3],[0,0],[3,1],[4,1],[5,5],[2,2]],"size":3,"solutions":28,"spl":16,"time":0.00029399999766610563},"132":{"color":5,"errors":143,"pairs":[[5,3],[5,2],[3,0],[1,0],[3,4],[2,2],[4,4],[3,5],[3,1],[5,1]],"size":3,"solutions":220,"spl":9,"time":0.001281999982893467},"133":{"color":6,"errors":107,"pairs":[[2,4],[4,4],[2,1],[3,2],[4,5],[3,5],[1,1],[0,0],[5,3],[4,1],[5,0],[1,0]],"size":3,"solutions":23,"spl":15,"time":0.0002479999966453761},"134":{"color":3,"errors":985,"pairs":[[5,5],[2,3],[3,4],[5,3],[0,0],[5,2]],"size":3,"solutions":1202,"spl":14,"time":0.003309000050649047},"135":{"color":3,"errors":3975,"pairs":[[2,3],[1,1],[3,2],[3,3],[3,4],[1,2]],"size":3,"solutions":617,"spl":5,"time":0.003160000080242753},"136":{"color":3,"errors":2543,"pairs":[[2,4],[4,5],[1,0],[1,1],[3,2],[4,1]],"size":3,"solutions":2064,"spl":5,"time":0.0035000001080334187},"137":{"color":3,"errors":1135,"pairs":[[4,0],[4,3],[0,0],[2,3],[4,1],[4,4]],"size":3,"solutions":233,"spl":13,"time":0.0018609999679028988},"138":{"color":3,"errors":661,"pairs":[[2,2],[3,5],[4,2],[0,0],[4,4],[5,2]],"size":3,"solutions":524,"spl":12,"time":0.002309999894350767},"139":{"color":3,"errors":317,"pairs":[[4,0],[2,4],[3,1],[4,4],[4,5],[5,4]],"size":3,"solutions":474,"spl":12,"time":0.002300000051036477},"14":{"color":3,"errors":2161,"pairs":[[0,0],[3,3],[1,1],[3,1],[3,0],[2,2]],"size":3,"solutions":204,"spl":12,"time":0.0},"140":{"color":3,"errors":424,"pairs":[[5,0],[3,5],[1,1],[5,1],[5,2],[3,3]],"size":3,"solutions":193,"spl":15,"time":0.0013180000241845846},"141":{"color":3,"errors":1077,"pairs":[[5,3],[4,1],[2,3],[2,2],[4,5],[1,1]],"size":3,"solutions":76,"spl":8,"time":0.0011030000168830156},"142":{"color":4,"errors":178,"pairs":[[5,4],[3,4],[2,3],[3,3],[1,1],[3,1],[4,2],[4,4]],"size":3,"solutions":16,"spl":10,"time":0.00024500000290572643},"143":{"color":4,"errors":698,"pairs":[[1,0],[2,0],[1,1],[3,4],[3,5],[3,2],[3,0],[5,2]],"size":3,"solutions":58,"spl":12,"time":0.0007960000075399876},"144":{"color":3,"errors":333,"pairs":[[3,2],[5,3],[3,4],[4,4],[5,1],[3,0]],"size":3,"solutions":1970,"spl":7,"time":0.0037140001077204943},"145":{"color":3,"errors":716,"pairs":[[1,2],[3,2],[5,1],[4,3],[4,5],[5,2]],"size":3,"solutions":404,"spl":11,"time":0.001686000032350421},"146":{"color":3,"errors":950,"pairs":[[3,2],[5,1],[0,0],[2,1],[3,1],[5,0]],"size":3,"solutions":1873,"spl":9,"time":0.00317199993878603},"147":{"color":3,"errors":869,"pairs":[[5,5],[3,4],[5,0],[5,1],[1,2],[4,3]],"size":3,"solutions":552,"spl":9,"time":0.002171000000089407},"148":{"color":3,"errors":582,"pairs":[[3,4],[5,4],[4,3],[2,1],[4,2],[1,0]],"size":3,"solutions":292,"spl":10,"time":0.001820000004954636},"149":{"color":3,"errors":1057,"pairs":[[3,4],[3,1],[5,2],[3,3],[3,5],[0,0]],"size":3,"solutions":275,"spl":10,"time":0.0016479999758303165},"15":{"color":3,"errors":813,"pairs":[[3,5],[5,4],[5,3],[5,2],[1,0],[3,4]],"size":3,"solutions":538,"spl":7,"time":0.0},"150":{"color":4,"errors":130,"pairs":[[3,0],[4,1],[0,0],[2,4],[5,2],[2,1],[4,3],[3,3]],"size":3,"solutions":38,"spl":9,"time":0.0003000000142492354},"151":{"color":4,"errors":50,"pairs":[[2,4],[4,3],[4,4],[3,0],[3,3],[4,2],[5,2],[4,0]],"size":3,"solutions":14,"spl":17,"time":0.00014800000644754618},"152":{"color":4,"errors":928,"pairs":[[4,4],[5,3],[2,3],[4,1],[1,1],[2,1],[3,5],[1,0]],"size":3,"solutions":28,"spl":11,"time":0.0007949999999254942},"153":{"color":3,"errors":558,"pairs":[[4,3],[4,5],[2,3],[5,5],[3,0],[2,2]],"size":3,"solutions":90,"spl":13,"time":0.0008870000019669533},"154":{"color":3,"errors":3798,"pairs":[[2,1],[4,5],[3,4],[5,1],[1,0],[1,2]],"size":3,"solutions":6,"spl":12,"time":0.0020810000132769346},"155":{"color":3,"errors":1000,"pairs":[[5,4],[2,2],[3,2],[1,1],[2,0],[4,5]],"size":3,"solutions":115,"spl":13,"time":0.0013699999544769526},"156":{"color":3,"errors":1135,"pairs":[[3,2],[2,0],[4,1],[3,1],[1,1],[2,4]],"size":3,"solutions":112,"spl":10,"time":0.001361000002361834},"157":{"color":3,"errors":2744,"pairs":[[3,5],[4,4],[0,0],[1,2],[5,0],[4,3]],"size":3,"solutions":3210,"spl":7,"time":0.004860999993979931},"158":{"color":3,"errors":3476,"pairs":[[2,3],[1,2],[3,5],[1,1],[3,4],[3,1]],"size":3,"solutions":234,"spl":15,"time":0.0025319999549537897},"159":{"color":3,"errors":2791,"pairs":[[1,0],[1,1],[2,1],[5,4],[2,2],[3,5]],"size":3,"solutions":2110,"spl":10,"time":0.003865000093355775},"16":{"color":3,"errors":711,"pairs":[[3,2],[3,4],[4,1],[1,0],[2,2],[4,4]],"size":3,"solutions":344,"spl":11,"time":0.0},"160":{"color":4,"errors":3568,"pairs":[[1,0],[2,1],[5,1],[2,2],[2,4],[0,0],[5,3],[5,2]],"size":3,"solutions":298,"spl":9,"time":0.0021669999696314335},"161":{"color":4,"errors":131,"pairs":[[2,2],[3,1],[5,4],[2,3],[3,4],[3,5],[4,1],[4,5]],"size":3,"solutions":22,"spl":17,"time":0.0002840000088326633},"162":{"color":4,"errors":1869,"pairs":[[1,1],[2,4],[0,0],[1,2],[3,5],[4,4],[5,4],[5,2]],"size":3,"solutions":386,"spl":7,"time":0.0022849999368190765},"163":{"color":4,"errors":338,"pairs":[[5,3],[5,4],[3,3],[5,5],[1,0],[1,1],[3,5],[3,4]],"size":3,"solutions":387,"spl":7,"time":0.0022239999379962683},"164":{"color":3,"errors":1543,"pairs":[[5,0],[5,4],[0,0],[2,1],[3,1],[4,0]],"size":3,"solutions":1370,"spl":9,"time":0.0031079999171197414},"165":{"color":3,"errors":1863,"pairs":[[5,3],[3,5],[2,3],[3,2],[0,0],[5,0]],"size":3,"solutions":3430,"spl":11,"time":0.0054350001737475395},"166":{"color":3,"errors":393,"pairs":[[2,2],[4,5],[1,1],[3,1],[4,0],[4,4]],"size":3,"solutions":24,"spl":17,"time":0.0004180000105407089},"167":{"color":3,"errors":969,"pairs":[[2,2],[5,5],[1,2],[3,1],[3,4],[4,0]],"size":3,"solutions":162,"spl":13,"time":0.0014400000218302011},"168":{"color":3,"errors":3717,"pairs":[[1,1],[1,2],[5,2],[2,0],[3,2],[5,0]],"size":3,"solutions":128,"spl":11,"time":0.002199999988079071},"169":{"color":3,"errors":2281,"pairs":[[2,1],[3,5],[2,4],[5,4],[2,2],[2,3]],"size":3,"solutions":112,"spl":17,"time":0.0021359999664127827},"17":{"color":3,"errors":1479,"pairs":[[1,1],[2,2],[1,0],[5,4],[4,1],[5,5]],"size":3,"solutions":140,"spl":15,"time":0.0},"170":{"color":3,"errors":2153,"pairs":[[3,5],[4,1],[3,1],[4,5],[1,1],[1,2]],"size":3,"solutions":414,"spl":14,"time":0.0018439999548718333},"171":{"color":4,"errors":316,"pairs":[[5,0],[2,1],[2,4],[5,1],[4,2],[1,1],[3,0],[1,0]],"size":3,"solutions":49,"spl":17,"time":0.0005280000041238964},"172":{"color":4,"errors":486,"pairs":[[3,0],[4,5],[1,2],[1,1],[4,4],[4,3],[2,1],[3,5]],"size":3,"solutions":104,"spl":14,"time":0.0009580000187270343},"173":{"color":4,"errors":561,"pairs":[[2,1],[2,2],[4,2],[3,3],[2,3],[3,4],[5,4],[1,0]],"size":3,"solutions":85,"spl":12,"time":0.000914999982342124},"174":{"color":4,"errors":991,"pairs":[[3,5],[3,4],[3,1],[3,3],[2,1],[1,2],[4,3],[0,0]],"size":3,"solutions":296,"spl":12,"time":0.0017239999724552035},"175":{"color":5,"errors":238,"pairs":[[2,2],[5,4],[3,4],[3,5],[2,4],[1,1],[1,2],[4,1],[5,0],[5,1]],"size":3,"solutions":41,"spl":14,"time":0.0004490000137593597},"176":{"color":3,"errors":308,"pairs":[[2,4],[3,1],[5,0],[4,1],[1,0],[4,0]],"size":3,"solutions":2098,"spl":9,"time":0.0035600000992417336},"177":{"color":3,"errors":757,"pairs":[[4,4],[2,1],[5,2],[3,1],[1,1],[3,0]],"size":3,"solutions":642,"spl":10,"time":0.0019990000873804092},"178":{"color":3,"errors":1216,"pairs":[[2,4],[2,2],[3,2],[4,2],[3,1],[1,0]],"size":3,"solutions":711,"spl":6,"time":0.0021869998890906572},"179":{"color":3,"errors":315,"pairs":[[2,4],[4,2],[3,1],[4,4],[3,5],[3,3]],"size":3,"solutions":192,"spl":12,"time":0.0012390000047162175},"18":{"color":3,"errors":4276,"pairs":[[5,3],[4,1],[1,1],[2,2],[0,0],[2,3]],"size":3,"solutions":682,"spl":8,"time":0.0},"180":{"color":3,"errors":544,"pairs":[[4,5],[3,2],[1,0],[5,1],[3,5],[3,4]],"size":3,"solutions":2394,"spl":10,"time":0.0041589997708797455},"181":{"color":3,"errors":399,"pairs":[[5,2],[5,5],[4,5],[4,2],[5,1],[2,0]],"size":3,"solutions":3135,"spl":10,"time":0.0049589998088777065},"182":{"color":3,"errors":1872,"pairs":[[3,2],[2,1],[5,0],[2,4],[5,3],[3,4]],"size":3,"solutions":1302,"spl":12,"time":0.0033340000081807375},"183":{"color":3,"errors":675,"pairs":[[5,3],[2,3],[2,1],[4,1],[3,5],[3,3]],"size":3,"solutions":330,"spl":9,"time":0.0021120000164955854},"184":{"color":3,"errors":469,"pairs":[[1,2],[4,3],[3,0],[4,0],[5,2],[3,4]],"size":3,"solutions":165,"spl":10,"time":0.001180000021122396},"185":{"color":4,"errors":409,"pairs":[[5,3],[3,5],[5,0],[4,1],[2,1],[4,0],[1,1],[2,0]],"size":3,"solutions":630,"spl":11,"time":0.002308000111952424},"186":{"color":4,"errors":256,"pairs":[[5,5],[4,5],[5,4],[1,2],[4,0],[2,3],[3,2],[5,2]],"size":3,"solutions":92,"spl":13,"time":0.0007309999782592058},"187":{"color":5,"errors":208,"pairs":[[3,4],[1,2],[2,1],[1,1],[4,1],[3,0],[2,3],[4,3],[5,5],[4,4]],"size":3,"solutions":16,"spl":11,"time":0.0002579999854788184},"188":{"color":3,"errors":204,"pairs":[[4,3],[4,5],[1,2],[5,4],[4,2],[3,4]],"size":3,"solutions":318,"spl":13,"time":0.0018769999733194709},"189":{"color":3,"errors":3658,"pairs":[[1,1],[2,1],[5,2],[4,4],[5,1],[0,0]],"size":3,"solutions":2102,"spl":10,"time":0.004381000064313412},"19":{"color":3,"errors":413,"pairs":[[5,1],[1,1],[3,1],[5,4],[3,4],[4,3]],"size":3,"solutions":234,"spl":13,"time":0.0},"190":{"color":3,"errors":317,"pairs":[[5,3],[3,2],[5,0],[4,1],[1,1],[4,4]],"size":3,"solutions":150,"spl":8,"time":0.0010389999952167273},"191":{"color":3,"errors":494,"pairs":[[3,3],[5,3],[2,4],[3,0],[3,4],[3,1]],"size":3,"solutions":84,"spl":11,"time":0.0007960000075399876},"192":{"color":3,"errors":527,"pairs":[[1,2],[4,2],[3,3],[5,1],[3,0],[3,4]],"size":3,"solutions":112,"spl":15,"time":0.0008880000095814466},"193":{"color":3,"errors":704,"pairs":[[5,0],[3,0],[4,5],[2,3],[5,5],[3,3]],"size":3,"solutions":928,"spl":9,"time":0.002268000040203333},"194":{"color":3,"errors":8908,"pairs":[[5,1],[5,2],[0,0],[1,1],[2,2],[1,2]],"size":3,"solutions":548,"spl":6,"time":0.003329999977722764},"195":{"color":3,"errors":2143,"pairs":[[4,4],[0,0],[1,2],[5,4],[2,0],[4,0]],"size":3,"solutions":130,"spl":12,"time":0.00203000009059906},"196":{"color":3,"errors":1659,"pairs":[[3,1],[5,5],[1,2],[1,0],[4,2],[4,4]],"size":3,"solutions":722,"spl":10,"time":0.0027230000123381615},"197":{"color":4,"errors":311,"pairs":[[3,4],[2,3],[4,3],[3,2],[4,5],[1,2],[5,0],[2,1]],"size":3,"solutions":54,"spl":10,"time":0.0005590000073425472},"198":{"color":5,"errors":97,"pairs":[[5,1],[4,0],[1,1],[3,0],[4,5],[3,4],[4,3],[5,2],[2,3],[2,0]],"size":3,"solutions":4,"spl":14,"time":0.00011800000356743112},"199":{"color":5,"errors":50,"pairs":[[5,1],[2,1],[4,0],[1,0],[3,3],[4,4],[5,3],[2,3],[2,4],[5,4]],"size":3,"solutions":3,"spl":17,"time":6.70000008540228e-05},"2":{"color":3,"errors":1334,"pairs":[[4,1],[3,4],[2,3],[2,2],[2,0],[3,5]],"size":3,"solutions":178,"spl":10,"time":0.0},"20":{"color":3,"errors":1298,"pairs":[[4,1],[5,4],[2,4],[2,0],[5,2],[2,1]],"size":3,"solutions":295,"spl":14,"time":0.0},"21":{"color":3,"errors":1074,"pairs":[[5,4],[5,1],[5,5],[1,1],[2,4],[2,1]],"size":3,"solutions":8,"spl":13,"time":0.0},"22":{"color":4,"errors":105,"pairs":[[2,0],[1,0],[3,2],[3,3],[5,2],[4,0],[4,1],[2,1]],"size":3,"solutions":154,"spl":7,"time":0.0},"23":{"color":4,"errors":487,"pairs":[[5,0],[3,1],[1,2],[4,3],[4,5],[5,2],[2,0],[2,3]],"size":3,"solutions":4,"spl":15,"time":0.0},"24":{"color":4,"errors":291,"pairs":[[5,3],[4,5],[3,2],[5,1],[1,2],[4,4],[2,1],[3,0]],"size":3,"solutions":42,"spl":12,"time":0.0},"25":{"color":3,"errors":5516,"pairs":[[2,3],[5,0],[3,4],[0,0],[5,4],[5,5]],"size":3,"solutions":1784,"spl":11,"time":0.0},"26":{"color":3,"errors":3149,"pairs":[[0,0],[2,1],[2,0],[2,3],[3,3],[4,3]],"size":3,"solutions":613,"spl":9,"time":0.0},"27":{"color":3,"errors":910,"pairs":[[2,1],[2,2],[3,4],[3,0],[5,2],[2,0]],"size":3,"solutions":16,"spl":17,"time":0.0},"28":{"color":3,"errors":942,"pairs":[[1,0],[4,4],[4,2],[2,2],[3,4],[3,2]],"size":3,"solutions":84,"spl":12,"time":0.0},"29":{"color":3,"errors":372,"pairs":[[5,5],[3,3],[1,1],[3,0],[5,2],[5,3]],"size":3,"solutions":715,"spl":8,"time":0.0},"3":{"color":3,"errors":1210,"pairs":[[3,2],[5,5],[0,0],[5,0],[2,1],[4,4]],"size":3,"solutions":1122,"spl":14,"time":0.0},"30":{"color":3,"errors":2493,"pairs":[[5,3],[5,5],[1,1],[3,5],[3,0],[3,4]],"size":3,"solutions":95,"spl":11,"time":0.0},"31":{"color":3,"errors":497,"pairs":[[4,5],[3,2],[4,2],[1,0],[5,0],[5,4]],"size":3,"solutions":536,"spl":13,"time":0.0},"32":{"color":4,"errors":358,"pairs":[[5,0],[4,3],[1,1],[4,1],[1,0],[4,5],[3,3],[2,3]],"size":3,"solutions":20,"spl":14,"time":0.0},"33":{"color":4,"errors":2428,"pairs":[[4,4],[4,5],[2,4],[1,0],[0,0],[1,2],[4,0],[5,2]],"size":3,"solutions":1314,"spl":8,"time":0.0},"34":{"color":5,"errors":178,"pairs":[[5,5],[4,1],[4,2],[2,3],[4,5],[3,4],[3,0],[1,1],[2,0],[1,0]],"size":3,"solutions":10,"spl":14,"time":0.0},"35":{"color":3,"errors":206,"pairs":[[5,2],[3,4],[5,0],[2,0],[3,1],[4,0]],"size":3,"solutions":180,"spl":13,"time":0.0010130000300705433},"36":{"color":5,"errors":144,"pairs":[[4,5],[5,4],[3,5],[0,0],[5,2],[3,3],[3,2],[5,1],[5,0],[2,3]],"size":3,"solutions":39,"spl":17,"time":0.0003769999893847853},"37":{"color":5,"errors":43,"pairs":[[3,3],[4,5],[2,2],[4,0],[4,3],[5,5],[5,3],[5,2],[2,0],[1,2]],"size":3,"solutions":29,"spl":14,"time":0.0002530000056140125},"38":{"color":3,"errors":253,"pairs":[[4,0],[4,1],[3,1],[4,5],[2,1],[5,3]],"size":3,"solutions":115,"spl":13,"time":0.0007699999841861427},"39":{"color":3,"errors":1277,"pairs":[[2,4],[2,2],[5,2],[4,0],[1,1],[3,0]],"size":3,"solutions":1979,"spl":8,"time":0.004112000111490488},"4":{"color":3,"errors":2387,"pairs":[[2,4],[3,4],[5,2],[3,3],[1,0],[1,2]],"size":3,"solutions":2058,"spl":7,"time":0.0},"40":{"color":3,"errors":2600,"pairs":[[2,4],[1,2],[3,2],[2,0],[5,1],[5,3]],"size":3,"solutions":700,"spl":6,"time":0.0027089999057352543},"41":{"color":3,"errors":5079,"pairs":[[3,1],[3,2],[0,0],[2,3],[5,5],[5,0]],"size":3,"solutions":766,"spl":9,"time":0.002876000013202429},"42":{"color":3,"errors":6688,"pairs":[[5,2],[5,4],[0,0],[1,0],[5,1],[1,1]],"size":3,"solutions":2311,"spl":7,"time":0.005326999817043543},"43":{"color":3,"errors":1202,"pairs":[[5,0],[2,3],[5,5],[5,1],[3,4],[4,3]],"size":3,"solutions":1077,"spl":12,"time":0.0030269999988377094},"44":{"color":4,"errors":188,"pairs":[[5,4],[3,2],[1,0],[2,4],[4,3],[3,1],[3,0],[4,1]],"size":3,"solutions":14,"spl":13,"time":0.0002410000015515834},"45":{"color":4,"errors":1309,"pairs":[[3,5],[1,1],[2,0],[1,0],[2,3],[3,0],[5,2],[4,3]],"size":3,"solutions":108,"spl":10,"time":0.0013559999642893672},"46":{"color":4,"errors":188,"pairs":[[3,5],[4,1],[2,3],[5,1],[5,5],[4,4],[4,0],[5,0]],"size":3,"solutions":321,"spl":14,"time":0.0018319999799132347},"47":{"color":3,"errors":2597,"pairs":[[2,4],[3,1],[0,0],[2,1],[4,3],[5,2]],"size":3,"solutions":110,"spl":9,"time":0.002093000104650855},"48":{"color":3,"errors":731,"pairs":[[3,1],[5,3],[4,3],[2,0],[2,3],[5,5]],"size":3,"solutions":218,"spl":12,"time":0.0015849999617785215},"49":{"color":3,"errors":1175,"pairs":[[3,1],[4,2],[4,3],[2,1],[0,0],[3,2]],"size":3,"solutions":56,"spl":15,"time":0.000965000013820827},"5":{"color":3,"errors":923,"pairs":[[5,3],[2,3],[3,2],[3,4],[2,0],[4,4]],"size":3,"solutions":188,"spl":14,"time":0.0},"50":{"color":3,"errors":324,"pairs":[[4,5],[3,4],[3,3],[5,1],[4,2],[1,1]],"size":3,"solutions":20,"spl":17,"time":0.0003440000000409782},"51":{"color":3,"errors":524,"pairs":[[2,4],[4,0],[2,2],[4,3],[5,0],[3,5]],"size":3,"solutions":284,"spl":15,"time":0.0018619999755173922},"52":{"color":4,"errors":204,"pairs":[[1,1],[1,2],[5,0],[5,1],[5,4],[2,1],[4,2],[4,4]],"size":3,"solutions":4,"spl":11,"time":0.00015999999595806003},"53":{"color":4,"errors":1808,"pairs":[[3,5],[4,5],[3,2],[2,1],[1,2],[5,2],[1,1],[2,4]],"size":3,"solutions":189,"spl":13,"time":0.00203000009059906},"54":{"color":4,"errors":410,"pairs":[[2,4],[3,3],[5,0],[1,2],[5,2],[3,1],[4,2],[2,1]],"size":3,"solutions":64,"spl":15,"time":0.0006409999914467335},"55":{"color":5,"errors":212,"pairs":[[1,1],[4,1],[5,4],[3,5],[1,0],[2,4],[3,1],[3,3],[2,0],[5,1]],"size":3,"solutions":2,"spl":18,"time":0.00016700000560376793},"56":{"color":5,"errors":152,"pairs":[[5,4],[4,5],[1,0],[2,0],[4,2],[5,2],[1,1],[3,4],[4,4],[2,3]],"size":3,"solutions":3,"spl":12,"time":0.00013699999544769526},"57":{"color":3,"errors":588,"pairs":[[5,5],[3,1],[5,3],[4,4],[0,0],[2,0]],"size":3,"solutions":360,"spl":10,"time":0.00043700000969693065},"58":{"color":3,"errors":278,"pairs":[[5,2],[4,0],[4,2],[3,1],[5,0],[4,1]],"size":3,"solutions":1032,"spl":12,"time":0.0011490000179037452},"59":{"color":3,"errors":588,"pairs":[[5,4],[5,3],[3,1],[4,4],[2,3],[3,3]],"size":3,"solutions":405,"spl":7,"time":0.000539999979082495},"6":{"color":3,"errors":1996,"pairs":[[1,1],[4,2],[5,5],[4,3],[2,4],[2,0]],"size":3,"solutions":421,"spl":11,"time":0.0},"60":{"color":3,"errors":137,"pairs":[[4,5],[3,4],[3,3],[4,1],[3,0],[5,3]],"size":3,"solutions":471,"spl":10,"time":0.0005019999807700515},"61":{"color":3,"errors":1587,"pairs":[[3,2],[2,2],[1,1],[4,4],[5,4],[1,0]],"size":3,"solutions":766,"spl":12,"time":0.0010389999952167273},"62":{"color":4,"errors":244,"pairs":[[3,0],[4,4],[5,0],[5,4],[1,2],[0,0],[4,0],[4,3]],"size":3,"solutions":77,"spl":14,"time":0.00012799999967683107},"63":{"color":4,"errors":683,"pairs":[[5,2],[5,0],[4,2],[4,4],[1,2],[0,0],[3,0],[3,3]],"size":3,"solutions":393,"spl":8,"time":0.0005150000215508044},"64":{"color":3,"errors":471,"pairs":[[4,4],[2,3],[3,5],[5,3],[3,3],[2,1]],"size":3,"solutions":286,"spl":8,"time":0.0017040000529959798},"65":{"color":3,"errors":920,"pairs":[[4,4],[2,3],[3,2],[2,1],[5,3],[5,2]],"size":3,"solutions":742,"spl":5,"time":0.002612000098451972},"66":{"color":3,"errors":1870,"pairs":[[4,3],[5,3],[5,4],[0,0],[3,1],[5,0]],"size":3,"solutions":1159,"spl":10,"time":0.0029800001066178083},"67":{"color":3,"errors":805,"pairs":[[3,3],[5,4],[3,2],[4,2],[5,5],[1,2]],"size":3,"solutions":432,"spl":8,"time":0.0022750000935047865},"68":{"color":3,"errors":1230,"pairs":[[2,4],[4,2],[2,3],[4,4],[3,1],[1,0]],"size":3,"solutions":118,"spl":11,"time":0.0015219999477267265},"69":{"color":3,"errors":165,"pairs":[[5,3],[2,1],[3,2],[4,1],[4,0],[4,5]],"size":3,"solutions":91,"spl":14,"time":0.000610999995842576},"7":{"color":3,"errors":614,"pairs":[[4,0],[5,5],[3,1],[2,1],[1,1],[4,1]],"size":3,"solutions":105,"spl":15,"time":0.0},"70":{"color":4,"errors":1912,"pairs":[[5,5],[5,3],[3,1],[1,0],[0,0],[2,1],[5,2],[3,5]],"size":3,"solutions":349,"spl":13,"time":0.002025000052526593},"71":{"color":4,"errors":926,"pairs":[[2,4],[2,3],[2,1],[5,5],[4,1],[3,2],[1,2],[3,1]],"size":3,"solutions":60,"spl":14,"time":0.0008290000259876251},"72":{"color":4,"errors":231,"pairs":[[4,2],[3,3],[4,1],[2,1],[4,4],[1,0],[3,2],[2,2]],"size":3,"solutions":12,"spl":9,"time":0.00025599999935366213},"73":{"color":5,"errors":1107,"pairs":[[3,1],[2,1],[1,1],[1,0],[2,4],[3,2],[3,5],[2,0],[5,5],[5,3]],"size":3,"solutions":70,"spl":15,"time":0.0011320000048726797},"74":{"color":3,"errors":2261,"pairs":[[3,0],[2,3],[5,5],[4,4],[1,2],[3,5]],"size":3,"solutions":1170,"spl":8,"time":0.003080999944359064},"75":{"color":3,"errors":4341,"pairs":[[3,4],[1,2],[2,0],[1,0],[5,0],[3,5]],"size":3,"solutions":390,"spl":11,"time":0.0028260000981390476},"76":{"color":3,"errors":496,"pairs":[[4,3],[0,0],[2,2],[4,5],[4,4],[4,0]],"size":3,"solutions":184,"spl":17,"time":0.0013620000099763274},"77":{"color":3,"errors":909,"pairs":[[3,0],[4,2],[2,0],[1,0],[3,4],[2,3]],"size":3,"solutions":1252,"spl":5,"time":0.0028280001133680344},"78":{"color":3,"errors":822,"pairs":[[3,4],[3,2],[2,3],[4,3],[5,1],[2,2]],"size":3,"solutions":156,"spl":11,"time":0.0012629999546334147},"79":{"color":4,"errors":308,"pairs":[[5,4],[5,2],[2,1],[4,5],[4,0],[5,0],[2,3],[4,3]],"size":3,"solutions":82,"spl":11,"time":0.0007239999831654131},"8":{"color":3,"errors":701,"pairs":[[3,0],[4,1],[3,5],[5,3],[1,1],[2,0]],"size":3,"solutions":1637,"spl":8,"time":0.0},"80":{"color":4,"errors":150,"pairs":[[3,2],[4,5],[4,2],[0,0],[3,4],[3,5],[2,2],[4,1]],"size":3,"solutions":36,"spl":16,"time":0.0003640000068116933},"81":{"color":4,"errors":666,"pairs":[[4,2],[5,1],[1,0],[5,0],[3,3],[2,1],[5,4],[1,1]],"size":3,"solutions":390,"spl":12,"time":0.002423000056296587},"82":{"color":3,"errors":1390,"pairs":[[1,2],[1,0],[5,3],[3,3],[3,2],[3,0]],"size":3,"solutions":1207,"spl":6,"time":0.0029090000316500664},"83":{"color":3,"errors":1083,"pairs":[[3,2],[2,4],[4,0],[1,0],[4,4],[2,1]],"size":3,"solutions":247,"spl":11,"time":0.0022249999456107616},"84":{"color":3,"errors":2281,"pairs":[[2,2],[3,1],[2,1],[1,2],[1,0],[4,2]],"size":3,"solutions":486,"spl":9,"time":0.0021279999054968357},"85":{"color":3,"errors":1401,"pairs":[[2,2],[1,0],[4,2],[4,1],[4,3],[1,1]],"size":3,"solutions":110,"spl":15,"time":0.0015640000347048044},"86":{"color":3,"errors":2831,"pairs":[[4,2],[2,4],[2,3],[1,1],[3,5],[2,2]],"size":3,"solutions":494,"spl":12,"time":0.0026650000363588333},"87":{"color":3,"errors":555,"pairs":[[3,2],[4,0],[2,3],[5,2],[4,5],[2,0]],"size":3,"solutions":46,"spl":14,"time":0.0005549999768845737},"88":{"color":4,"errors":1280,"pairs":[[0,0],[1,0],[4,2],[4,3],[3,5],[5,5],[5,1],[2,0]],"size":3,"solutions":2346,"spl":8,"time":0.003739000065252185},"89":{"color":3,"errors":1773,"pairs":[[4,4],[1,1],[4,3],[3,5],[1,2],[2,4]],"size":3,"solutions":596,"spl":9,"time":0.002345999935641885},"9":{"color":3,"errors":131,"pairs":[[5,5],[3,5],[4,4],[2,2],[5,2],[5,4]],"size":3,"solutions":587,"spl":7,"time":0.0},"90":{"color":3,"errors":618,"pairs":[[5,3],[2,2],[5,5],[4,2],[0,0],[3,0]],"size":3,"solutions":670,"spl":13,"time":0.0023169999476522207},"91":{"color":3,"errors":832,"pairs":[[4,0],[2,2],[3,1],[1,0],[5,4],[2,3]],"size":3,"solutions":490,"spl":10,"time":0.002406999934464693},"92":{"color":3,"errors":1279,"pairs":[[4,5],[2,4],[3,2],[4,3],[1,2],[3,1]],"size":3,"solutions":793,"spl":7,"time":0.002222999930381775},"93":{"color":3,"errors":654,"pairs":[[2,2],[3,1],[3,0],[4,1],[2,3],[3,4]],"size":3,"solutions":631,"spl":5,"time":0.002211000071838498},"94":{"color":3,"errors":1022,"pairs":[[3,3],[4,1],[2,0],[3,4],[5,4],[1,0]],"size":3,"solutions":34,"spl":14,"time":0.0008019999950192869},"95":{"color":4,"errors":347,"pairs":[[2,1],[2,3],[5,5],[3,5],[3,0],[4,0],[3,2],[3,1]],"size":3,"solutions":649,"spl":6,"time":0.0019710001070052385},"96":{"color":4,"errors":161,"pairs":[[2,3],[5,1],[3,2],[1,1],[4,3],[5,5],[4,4],[5,4]],"size":3,"solutions":7,"spl":18,"time":0.00017299999308306724},"97":{"color":4,"errors":595,"pairs":[[4,1],[5,1],[5,5],[5,4],[2,3],[2,2],[4,0],[1,1]],"size":3,"solutions":871,"spl":7,"time":0.0024170000106096268},"98":{"color":4,"errors":175,"pairs":[[4,4],[5,4],[3,1],[5,3],[5,2],[5,5],[1,0],[2,4]],"size":3,"solutions":16,"spl":20,"time":0.00024399999529123306},"99":{"color":4,"errors":1015,"pairs":[[0,0],[1,0],[2,0],[4,1],[3,1],[2,4],[4,3],[3,3]],"size":3,"solutions":640,"spl":9,"time":0.0020669999066740274}}